stemmabench/__init__.py
stemmabench/cli.py
stemmabench/config_parser.py
stemmabench/stemma_analyzer.py
stemmabench/stemma_generator.py
stemmabench/data/__init__.py
stemmabench/data/en_synonyms.json
stemmabench/textual_units/__init__.py
stemmabench/textual_units/sentence.py
stemmabench/textual_units/text.py
stemmabench/textual_units/word.py
tests/test_config_parser.py
tests/test_generate_tree.py
tests/test_text_units.py
stemmabench-0.0.1.dist-info/LICENSE
stemmabench-0.0.1.dist-info/METADATA
stemmabench-0.0.1.dist-info/WHEEL
stemmabench-0.0.1.dist-info/entry_points.txt
stemmabench-0.0.1.dist-info/top_level.txt
stemmabench-0.0.1.dist-info/RECORD
