Metadata-Version: 2.1
Name: stemmabench
Version: 0.0.1
Summary: Package for benching stemmatology algorithms
Requires-Python: >=3.8
License-File: LICENSE
Requires-Dist: loguru ==0.6.0
Requires-Dist: pydantic ==1.9.1
Requires-Dist: PyYAML ==6.0
Requires-Dist: typer ==0.4.1
Provides-Extra: dev
Requires-Dist: wheel ; extra == 'dev'
Requires-Dist: build ; extra == 'dev'
Requires-Dist: twine ; extra == 'dev'
Provides-Extra: test
Requires-Dist: pytest ; extra == 'test'
Requires-Dist: pytest-cov[all] ; extra == 'test'
Requires-Dist: pylint ==2.14.5 ; extra == 'test'
